workstation/__init__.py
workstation/config.py
workstation/core.py
workstation/machines.py
workstation/utils.py
workstation/cli/__init__.py
workstation/cli/__main__.py
workstation/cli/crud.py
cloud_workstation-0.3.0.dist-info/LICENSE.txt
cloud_workstation-0.3.0.dist-info/METADATA
cloud_workstation-0.3.0.dist-info/WHEEL
cloud_workstation-0.3.0.dist-info/entry_points.txt
cloud_workstation-0.3.0.dist-info/top_level.txt
cloud_workstation-0.3.0.dist-info/RECORD
